asilbek_kutubxona/__init__.py
asilbek_kutubxona/math_utils.py
asilbek_kutubxona/string_utils.py
asilbek_kutubxona-0.1.0.dist-info/licenses/LICENSE
asilbek_kutubxona-0.1.0.dist-info/METADATA
asilbek_kutubxona-0.1.0.dist-info/WHEEL
asilbek_kutubxona-0.1.0.dist-info/top_level.txt
asilbek_kutubxona-0.1.0.dist-info/RECORD
