Metadata-Version: 2.4
Name: asilbek_kutubxona
Version: 0.1.0
Summary: Oddiy matematik va string kutubxona
Author: Isming
Author-email: asilbek.sadullayev000@example.com
Requires-Python: >=3.6
License-File: LICENSE
Dynamic: author
Dynamic: author-email
Dynamic: license-file
Dynamic: requires-python
Dynamic: summary
